strawberry/__init__.py
strawberry/__main__.py
strawberry/aiohttp/__init__.py
strawberry/aiohttp/test/__init__.py
strawberry/aiohttp/test/client.py
strawberry/aiohttp/views.py
strawberry/annotation.py
strawberry/asgi/__init__.py
strawberry/asgi/test/__init__.py
strawberry/asgi/test/client.py
strawberry/chalice/__init__.py
strawberry/chalice/views.py
strawberry/channels/__init__.py
strawberry/channels/handlers/__init__.py
strawberry/channels/handlers/base.py
strawberry/channels/handlers/http_handler.py
strawberry/channels/handlers/ws_handler.py
strawberry/channels/router.py
strawberry/channels/testing.py
strawberry/cli/__init__.py
strawberry/cli/app.py
strawberry/cli/commands/__init__.py
strawberry/cli/commands/codegen.py
strawberry/cli/commands/dev.py
strawberry/cli/commands/export_schema.py
strawberry/cli/commands/locate_definition.py
strawberry/cli/commands/schema_codegen.py
strawberry/cli/commands/server.py
strawberry/cli/commands/upgrade/__init__.py
strawberry/cli/commands/upgrade/_fake_progress.py
strawberry/cli/commands/upgrade/_run_codemod.py
strawberry/cli/constants.py
strawberry/cli/dev_server.py
strawberry/cli/utils/__init__.py
strawberry/cli/utils/load_schema.py
strawberry/codegen/__init__.py
strawberry/codegen/exceptions.py
strawberry/codegen/plugins/__init__.py
strawberry/codegen/plugins/print_operation.py
strawberry/codegen/plugins/python.py
strawberry/codegen/plugins/typescript.py
strawberry/codegen/query_codegen.py
strawberry/codegen/types.py
strawberry/codemods/__init__.py
strawberry/codemods/annotated_unions.py
strawberry/codemods/maybe_optional.py
strawberry/codemods/replace_scalar_wrappers.py
strawberry/codemods/update_imports.py
strawberry/dataloader.py
strawberry/directive.py
strawberry/django/__init__.py
strawberry/django/apps.py
strawberry/django/context.py
strawberry/django/test/__init__.py
strawberry/django/test/client.py
strawberry/django/views.py
strawberry/exceptions/__init__.py
strawberry/exceptions/conflicting_arguments.py
strawberry_graphql-0.288.2.dist-info/METADATA
strawberry_graphql-0.288.2.dist-info/WHEEL
strawberry_graphql-0.288.2.dist-info/entry_points.txt
strawberry_graphql-0.288.2.dist-info/licenses/LICENSE
strawberry_graphql-0.288.2.dist-info/RECORD
